scripnix/__init__.py
scripnix/conf/alias.bash
scripnix/conf/bin.bash
scripnix/conf/conf.bash
scripnix/conf/func.bash
scripnix/conf/rc.bash
scripnix/conf/salias.bash
scripnix/conf/sbin.bash
scripnix/conf/sconf.bash
scripnix/pybin/__init__.py
scripnix/pybin/backup_file.py
scripnix/pybin/command_for_pid.py
scripnix/pybin/common_netmask.py
scripnix/pybin/describe_scripnix.py
scripnix/pybin/gather_cron_jobs.py
scripnix/pybin/hyphenate.py
scripnix/pybin/install_scripnix.py
scripnix/pybin/os_name.py
scripnix/pybin/top_level_pid.py
scripnix/pybin/whereis_scripnix.py
scripnix/shbin/find-grep
scripnix/shbin/is-remote-cnx
scripnix/shbin/locate-ll
scripnix/shbin/show-cron-jobs
scripnix/util/__init__.py
scripnix/util/command.py
scripnix/util/common.py
scripnix-0.1.12.data/scripts/find-grep
scripnix-0.1.12.data/scripts/is-remote-cnx
scripnix-0.1.12.data/scripts/locate-ll
scripnix-0.1.12.data/scripts/show-cron-jobs
scripnix-0.1.12.dist-info/DESCRIPTION.rst
scripnix-0.1.12.dist-info/METADATA
scripnix-0.1.12.dist-info/RECORD
scripnix-0.1.12.dist-info/WHEEL
scripnix-0.1.12.dist-info/entry_points.txt
scripnix-0.1.12.dist-info/metadata.json
scripnix-0.1.12.dist-info/top_level.txt
tests/__init__.py
tests/command.py
tests/common.py
tests/test_backup_file.py
tests/test_command.py
tests/test_command_for_pid.py
tests/test_common.py
tests/test_common_netmask.py
tests/test_describe_scripnix.py
tests/test_find_grep.py
tests/test_gather_cron_jobs.py
tests/test_hyphenate.py
tests/test_install_scripnix.py
tests/test_locate_ll.py
tests/test_os_name.py
tests/test_top_level_pid.py
tests/test_whereis_scripnix.py
