Metadata-Version: 2.0
Name: scripnix
Version: 0.1.12
Summary: Useful Python3 and bash shell scripts for macOS/BSD and *NIX. Useful to me, at any rate. YMMV.
Home-page: https://yukondude.github.io/Scripnix/
Author: Dave Rogers
Author-email: thedude@yukondude.com
License: GPLv3
Platform: MacOS
Platform: Linux
Classifier: Development Status :: 3 - Alpha
Classifier: Environment :: Console
Classifier: Intended Audience :: Developers
Classifier: Intended Audience :: System Administrators
Classifier: License :: OSI Approved :: GNU General Public License v3 (GPLv3)
Classifier: Natural Language :: English
Classifier: Operating System :: MacOS
Classifier: Operating System :: POSIX
Classifier: Operating System :: POSIX :: Linux
Classifier: Programming Language :: Python
Classifier: Programming Language :: Python :: 3
Classifier: Programming Language :: Python :: 3.3
Classifier: Programming Language :: Python :: 3.4
Classifier: Programming Language :: Python :: 3.5
Classifier: Programming Language :: Python :: 3.6
Classifier: Programming Language :: Unix Shell
Classifier: Topic :: System
Classifier: Topic :: System :: Archiving
Classifier: Topic :: System :: Systems Administration
Classifier: Topic :: Utilities
Requires-Dist: click (>=6.7)
Requires-Dist: psutil (>=5.1.1)
Provides-Extra: testing
Requires-Dist: coverage (>=4.3.4); extra == 'testing'
Requires-Dist: flake8 (>=3.2.1); extra == 'testing'
Requires-Dist: pytest (>=3.0.6); extra == 'testing'
Requires-Dist: pytest-cov (>=2.4.0); extra == 'testing'
Requires-Dist: pytest-flake8 (>=0.8.1); extra == 'testing'
